imagefield/__init__.py
imagefield/fields.py
imagefield/processing.py
imagefield/webp.py
imagefield/websafe.py
imagefield/widgets.py
imagefield/locale/de/LC_MESSAGES/django.mo
imagefield/locale/de/LC_MESSAGES/django.po
imagefield/management/__init__.py
imagefield/management/commands/__init__.py
imagefield/management/commands/process_imagefields.py
imagefield/static/imagefield/ppoi.css
imagefield/static/imagefield/ppoi.js
django_imagefield-0.22.0.dist-info/METADATA
django_imagefield-0.22.0.dist-info/WHEEL
django_imagefield-0.22.0.dist-info/licenses/LICENSE
django_imagefield-0.22.0.dist-info/RECORD
