Metadata-Version: 2.3
Name: django-imagefield
Version: 0.22.0
Summary: Image field for Django
Project-URL: Homepage, https://github.com/matthiask/django-imagefield/
Author-email: Matthias Kestenholz <mk@feinheit.ch>
License: BSD-3-Clause
Classifier: Environment :: Web Environment
Classifier: Framework :: Django
Classifier: Intended Audience :: Developers
Classifier: License :: OSI Approved :: BSD License
Classifier: Operating System :: OS Independent
Classifier: Programming Language :: Python
Classifier: Programming Language :: Python :: 3 :: Only
Classifier: Programming Language :: Python :: 3.10
Classifier: Programming Language :: Python :: 3.11
Classifier: Programming Language :: Python :: 3.12
Classifier: Programming Language :: Python :: 3.13
Classifier: Topic :: Internet :: WWW/HTTP :: Dynamic Content
Classifier: Topic :: Software Development
Classifier: Topic :: Software Development :: Libraries :: Application Frameworks
Requires-Python: >=3.10
Requires-Dist: pillow!=11,>=9
Provides-Extra: tests
Requires-Dist: coverage; extra == 'tests'
Requires-Dist: pillow; extra == 'tests'
